[{"codciclo":"ADG201","nombreciclo":"Gestión Administrativa","grado":"GMedio"},{"codciclo":"ADG201","nombreciclo":"Gestión Administrativa","grado":"GMedio"},{"codciclo":"ADG201","nombreciclo":"Gestión Administrativa","grado":"GMedio"},{"codciclo":"ADG201","nombreciclo":"Gestión Administrativa","grado":"GMedio"},{"codciclo":"ADG201","nombreciclo":"Gestión Administrativa","grado":"GMedio"},{"codciclo":"ADG201","nombreciclo":"Gestión Administrativa","grado":"GMedio"},{"codciclo":"ADG201","nombreciclo":"Gestión Administrativa","grado":"GMedio"},{"codciclo":"ADG201","nombreciclo":"Gestión Administrativa","grado":"GMedio"},{"codciclo":"ADG201","nombreciclo":"Gestión Administrativa","grado":"GMedio"},{"codciclo":"ADG201","nombreciclo":"Gestión Administrativa","grado":"GMedio"}]
